testguiui.py
test_py_gui-0.1.0.dist-info/licenses/LICENSE
test_py_gui-0.1.0.dist-info/METADATA
test_py_gui-0.1.0.dist-info/WHEEL
test_py_gui-0.1.0.dist-info/top_level.txt
test_py_gui-0.1.0.dist-info/RECORD
