Metadata-Version: 2.4
Name: test-py-gui
Version: 0.1.0
Summary: Add your description here
Requires-Python: >=3.13
License-File: LICENSE
Requires-Dist: pygubu>=0.38.2
Dynamic: license-file
